{
  "main": {
    "name": "Shivam Soni",
    "occupation": "Final Year B.Tech Student",
    "description": "Passionate about data analysis, web development, and marketing",
    "image": "profilepic.jpg",
    "bio": "Motivated and detail-oriented final-year B.Tech (CSE) student at Adina Institute of Science and Technology, Sagar. Passionate about data analysis, web development, and marketing. Skilled in Java, basic web development, and problem-solving. Looking to apply my technical and analytical expertise to impactful projects while growing professionally.",
    "contactmessage": "Get in touch with me for collaboration and opportunities!",
    "email": "shivamsoni01118@gmail.com",
    "phone": "7581021470",
    "address": {
      "street": "Sagar",
      "city": "Madhya Pradesh",
      "state": "India",
      "zip": "470002"
    },
    "website": "https://www.linkedin.com/in/shivam-soni-178b45242/",
    "resumedownload": "https://www.adina.edu.in/",
    "social": [
      {
        "name": "linkedin",
        "url": "https://www.linkedin.com/in/shivam-soni-178b45242/",
        "className": "fa fa-linkedin"
      }
    ]
  },
  "resume": {
    "skillmessage": "My Technical and Marketing Skills",
    "education": [
      {
        "school": "Adina Institute of Science and Technology",
        "degree": "Bachelor of Technology in Computer Science and Engineering",
        "graduated": "Present",
        "description": "Final year student with a focus on web development, data analysis, and problem-solving."
      },
      {
        "school": "Pearl Public Higher Secondary School",
        "degree": "Higher Secondary Education (Science Stream)",
        "graduated": "2021",
        "description": "Completed with 86%."
      },
      {
        "school": "Pearl Public Higher Secondary School",
        "degree": "Secondary Education",
        "graduated": "2019",
        "description": "Completed with 83.3%."
      }
    ],
    "work": [],
    "skills": [
      {
        "name": "Java",
        "level": "100%"
      },
      {
        "name": "C++",
        "level": "100%"
      },
      {
        "name": "Python",
        "level": "50%"
      },
      {
        "name": "HTML, CSS, JavaScript",
        "level": "100%"
      },
      {
        "name": "SQL",
        "level": "100%"
      },
      {
        "name": "Microsoft Excel & Google Sheets",
        "level": "75%"
      },
      {
        "name": "Google Ads (Basic)",
        "level": "50%"
      }
    ]
  },
  "certificates": [
    {
      "title": "Google Ads for Beginners",
      "issuer": "Coursera Project Network",
      "url": "https://coursera.org/verify/OUUSVH8EPD1Y"
    }
  ],
  "languages": [
    {
      "name": "English",
      "proficiency": "Intermediate"
    },
    {
      "name": "Hindi",
      "proficiency": "Native/Bilingual"
    }
  ]
}
